{
  "annotations": {
    "list": [
      {
        "builtIn": 1,
        "datasource": {"type": "grafana", "uid": "-- Grafana --"},
        "enable": true,
        "hide": true,
        "iconColor": "rgba(0, 211, 255, 1)",
        "name": "Annotations & Alerts",
        "type": "dashboard"
      }
    ]
  },
  "editable": false,
  "fiscalYearStartMonth": 0,
  "graphTooltip": 0,
  "id": null,
  "links": [],
  "liveNow": false,
  "panels": [
    {
      "datasource": {"type": "prometheus", "uid": "prometheus"},
      "description": "Replace this file with the full community dashboard from https://grafana.com/grafana/dashboards/1860 when convenient. This minimal placeholder covers CPU, memory, disk and network using the same node_exporter metrics.",
      "fieldConfig": {"defaults": {"color": {"mode": "palette-classic"}, "unit": "percent"}, "overrides": []},
      "gridPos": {"h": 8, "w": 12, "x": 0, "y": 0},
      "id": 1,
      "options": {"legend": {"displayMode": "list", "placement": "bottom", "showLegend": true}, "tooltip": {"mode": "single"}},
      "targets": [
        {
          "datasource": {"type": "prometheus", "uid": "prometheus"},
          "expr": "100 - (avg by (instance) (rate(node_cpu_seconds_total{mode=\"idle\"}[5m])) * 100)",
          "legendFormat": "{{instance}}",
          "refId": "A"
        }
      ],
      "title": "CPU usage %",
      "type": "timeseries"
    },
    {
      "datasource": {"type": "prometheus", "uid": "prometheus"},
      "fieldConfig": {"defaults": {"color": {"mode": "palette-classic"}, "unit": "percent"}, "overrides": []},
      "gridPos": {"h": 8, "w": 12, "x": 12, "y": 0},
      "id": 2,
      "options": {"legend": {"displayMode": "list", "placement": "bottom", "showLegend": true}, "tooltip": {"mode": "single"}},
      "targets": [
        {
          "datasource": {"type": "prometheus", "uid": "prometheus"},
          "expr": "100 * (1 - (node_memory_MemAvailable_bytes / node_memory_MemTotal_bytes))",
          "legendFormat": "{{instance}}",
          "refId": "A"
        }
      ],
      "title": "Memory usage %",
      "type": "timeseries"
    },
    {
      "datasource": {"type": "prometheus", "uid": "prometheus"},
      "fieldConfig": {"defaults": {"color": {"mode": "palette-classic"}, "unit": "percent"}, "overrides": []},
      "gridPos": {"h": 8, "w": 12, "x": 0, "y": 8},
      "id": 3,
      "options": {"legend": {"displayMode": "list", "placement": "bottom", "showLegend": true}, "tooltip": {"mode": "single"}},
      "targets": [
        {
          "datasource": {"type": "prometheus", "uid": "prometheus"},
          "expr": "100 - (node_filesystem_avail_bytes{fstype!~\"tmpfs|overlay\",mountpoint=\"/\"} / node_filesystem_size_bytes{fstype!~\"tmpfs|overlay\",mountpoint=\"/\"} * 100)",
          "legendFormat": "{{instance}} {{mountpoint}}",
          "refId": "A"
        }
      ],
      "title": "Root disk usage %",
      "type": "timeseries"
    },
    {
      "datasource": {"type": "prometheus", "uid": "prometheus"},
      "fieldConfig": {"defaults": {"color": {"mode": "palette-classic"}, "unit": "Bps"}, "overrides": []},
      "gridPos": {"h": 8, "w": 12, "x": 12, "y": 8},
      "id": 4,
      "options": {"legend": {"displayMode": "list", "placement": "bottom", "showLegend": true}, "tooltip": {"mode": "single"}},
      "targets": [
        {
          "datasource": {"type": "prometheus", "uid": "prometheus"},
          "expr": "rate(node_network_receive_bytes_total{device!~\"lo|docker.*|veth.*\"}[5m])",
          "legendFormat": "{{instance}} {{device}} in",
          "refId": "A"
        },
        {
          "datasource": {"type": "prometheus", "uid": "prometheus"},
          "expr": "rate(node_network_transmit_bytes_total{device!~\"lo|docker.*|veth.*\"}[5m])",
          "legendFormat": "{{instance}} {{device}} out",
          "refId": "B"
        }
      ],
      "title": "Network throughput",
      "type": "timeseries"
    }
  ],
  "refresh": "30s",
  "schemaVersion": 39,
  "tags": ["node-exporter", "whoknows"],
  "templating": {"list": []},
  "time": {"from": "now-1h", "to": "now"},
  "timepicker": {},
  "timezone": "",
  "title": "Node Exporter — WhoKnows",
  "uid": "whoknows-node",
  "version": 1,
  "weekStart": ""
}
